yt_transcripts/__init__.py
yt_transcripts/channel.py
yt_transcripts/cli.py
yt_transcripts/extractor.py
yt_transcripts/formatters.py
yt_transcripts/summarizer.py
yt_transcripts-0.2.0.dist-info/METADATA
yt_transcripts-0.2.0.dist-info/WHEEL
yt_transcripts-0.2.0.dist-info/entry_points.txt
yt_transcripts-0.2.0.dist-info/top_level.txt
yt_transcripts-0.2.0.dist-info/RECORD
