Metadata-Version: 2.4
Name: yt-transcripts
Version: 0.2.0
Summary: CLI tool for extracting transcripts from YouTube videos, playlists, and channels
Requires-Python: >=3.10
Requires-Dist: youtube-transcript-api>=0.6.0
Requires-Dist: yt-dlp>=2023.0.0
Provides-Extra: dev
Requires-Dist: pytest>=7.0; extra == "dev"
Provides-Extra: summarize
Requires-Dist: litellm>=1.30.0; extra == "summarize"
Requires-Dist: python-dotenv>=1.0.0; extra == "summarize"
